erhsh/__init__.py
erhsh/version.py
erhsh/common/__init__.py
erhsh/common/checkpoint.py
erhsh/ms/__init__.py
erhsh/ms/cli.py
erhsh/ms/version.py
erhsh/ms/demo/__init__.py
erhsh/ms/demo/cli.py
erhsh/ms/demo/demo_mgmt.py
erhsh/ms/demo/jupyter_template.ipynb
erhsh/ms/demo/version.py
erhsh/ms/demo/dataset/__init__.py
erhsh/ms/demo/dataset/ds_00_mocker.py
erhsh/ms/demo/dataset/ds_01_generator.py
erhsh/ms/demo/dataset/ds_02_mind.py
erhsh/ms/demo/dataset/ds_03_imagefolder.py
erhsh/ms/demo/dataset/ds_04_cifar10.py
erhsh/ms/demo/dataset/ds_05_mnist.py
erhsh/ms/demo/network/__init__.py
erhsh/ms/demo/network/net_00_simple.py
erhsh/ms/demo/network/net_01_lenet.py
erhsh/ms/demo/network/net_02_vgg.py
erhsh/ms/demo/operator/test_nn_Abs.py
erhsh/ms/demo/operator/test_nn_AvgPool2d.py
erhsh/ms/demo/operator/test_nn_Dropout.py
erhsh/ms/demo/resource/env.sh
erhsh/ms/demo/resource/proxy.sh
erhsh/ms/demo/training/train_00_simplenet.py
erhsh/ms/demo/training/train_01_lenet.py
erhsh/ms/ds/__init__.py
erhsh/ms/ds/ds_mocker.py
erhsh/ms/ds/ds_printer.py
erhsh/ms/ds/ds_wrapper.py
erhsh/ms/tools/__init__.py
erhsh/ms/tools/bin_tool.py
erhsh/ms/tools/ckpt.py
erhsh/ms/tools/hccl_tool.py
erhsh/ms/tools/hccl_tool_v1.py
erhsh/ms/train/__init__.py
erhsh/ms/train/_argparse.py
erhsh/ms/train/_callbacks.py
erhsh/ms/train/training.py
erhsh/pt/__init__.py
erhsh/pt/cli.py
erhsh/pt/version.py
erhsh/pt/demo/__init__.py
erhsh/pt/demo/cli.py
erhsh/pt/demo/demo_mgmt.py
erhsh/pt/demo/jupyter_template.ipynb
erhsh/pt/demo/version.py
erhsh/pt/demo/operator/test_00_base.py
erhsh/pt/demo/operator/test_01_abs.py
erhsh/pt/tools/__init__.py
erhsh/pt/tools/pth.py
erhsh/tools/__init__.py
erhsh/tools/bash_helper.py
erhsh/tools/cli.py
erhsh/tools/git_helper.py
erhsh/tools/jupyter_helper.py
erhsh/tools/version.py
erhsh/tools/vim_helper.py
erhsh/utils/__init__.py
erhsh/utils/calc_iou.py
erhsh/utils/file_util.py
erhsh/utils/img_comp_split.py
erhsh/utils/img_comp_split_helper.py
erhsh/utils/img_util.py
erhsh/utils/logger_util.py
erhsh_python-0.2.6.dist-info/LICENSE
erhsh_python-0.2.6.dist-info/METADATA
erhsh_python-0.2.6.dist-info/WHEEL
erhsh_python-0.2.6.dist-info/entry_points.txt
erhsh_python-0.2.6.dist-info/top_level.txt
erhsh_python-0.2.6.dist-info/RECORD
